teams_logger/__init__.py
teams_logger/core.py
teams_logger-0.5.1.dist-info/LICENSE
teams_logger-0.5.1.dist-info/METADATA
teams_logger-0.5.1.dist-info/WHEEL
teams_logger-0.5.1.dist-info/RECORD
