Metadata-Version: 2.3
Name: teams-logger
Version: 0.5.1
Summary: Microsoft Teams logging handler for Python
License: MIT
Author: Anes Foufa
Author-email: anes.foufa@upply.com
Requires-Python: >=3.8,<4.0
Classifier: License :: OSI Approved :: MIT License
Classifier: Programming Language :: Python :: 3
Classifier: Programming Language :: Python :: 3.8
Classifier: Programming Language :: Python :: 3.9
Classifier: Programming Language :: Python :: 3.10
Classifier: Programming Language :: Python :: 3.11
Classifier: Programming Language :: Python :: 3.12
Classifier: Programming Language :: Python :: 3.13
Classifier: Topic :: Communications :: Chat
Classifier: Topic :: System :: Logging
Requires-Dist: requests (>=2.32.0,<3.0.0)
Project-URL: Homepage, https://github.com/AnesFoufa/python-teams-logger
